sem6/__init__.py
sem6/adaboost.py
sem6/clustering.py
sem6/decisiontree.py
sem6/ensemble_classification.py
sem6/ensemble_regression.py
sem6/gradientboosting.py
sem6/lightgbm.py
sem6/linearreg.py
sem6/logisticreg.py
sem6/randomforest.py
sem6/svm.py
sem6/theory.py
sem6/xgb.py
sem6-5.0.0.dist-info/METADATA
sem6-5.0.0.dist-info/WHEEL
sem6-5.0.0.dist-info/top_level.txt
sem6-5.0.0.dist-info/RECORD
