Metadata-Version: 2.1
Name: sem6
Version: 5.0.0
Requires-Dist: numpy
